pyscada/__init__.py
pyscada/modbus/__init__.py
pyscada/modbus/admin.py
pyscada/modbus/apps.py
pyscada/modbus/device.py
pyscada/modbus/models.py
pyscada/modbus/signals.py
pyscada/modbus/worker.py
pyscada/modbus/migrations/0001_initial.py
pyscada/modbus/migrations/0002_auto_20160111_1802.py
pyscada/modbus/migrations/0003_auto_20160115_0918.py
pyscada/modbus/migrations/0004_auto_20160115_0920.py
pyscada/modbus/migrations/0005_auto_20170224_1249.py
pyscada/modbus/migrations/0006_auto_20170711_1326.py
pyscada/modbus/migrations/0007_extendedmodbusdevice_extendedmodbusvariable.py
pyscada/modbus/migrations/0008_auto_20190206_1507.py
pyscada/modbus/migrations/0009_add_device_protocol.py
pyscada/modbus/migrations/__init__.py
pyscada_modbus-0.8.0.dist-info/AUTHORS
pyscada_modbus-0.8.0.dist-info/LICENSE
pyscada_modbus-0.8.0.dist-info/METADATA
pyscada_modbus-0.8.0.dist-info/WHEEL
pyscada_modbus-0.8.0.dist-info/top_level.txt
pyscada_modbus-0.8.0.dist-info/RECORD
